<?xml version="1.0" encoding="utf-8"?>
<UITemplate>

    <Style path="Klang/Seed/UIForia/LoginFlow/LoginScreen/LoginScreen.style"/>

    <Style path="Klang/Seed/UIForia/Util.style" alias="util"/>
    <Style path="Klang/Seed/UIForia/KlangButton/KlangButton.style" alias="klang-button"/>
    
    <Contents style="container">

        <Image style="seed-logo" src="'Images/seed_pioneers_hgm_logo'"/>

        <Text style="text">SEED</Text>

        <Group style="util.horizontal" style.paddingTop="24f" style.paddingBottom="24f">
            <Input style="login-input" onValueChanged="SetUsername()" username.bindTo="onValueChanged"/>
            <Input style="login-input" password.bindTo="onValueChanged"/>
        </Group>

        <Group style="util.vertical-center" x-tooltip="blockId">
            
            <KlangButton style="klang-button.black" label="'Login'" onMouseDown="Login()"/>
            
            <Text style.paddingTop="24f" style.paddingBottom="24f" style.textFontSize="26">Or</Text>
            
            <KlangButton style="klang-button.outline" label="'Create Account'" onMouseDown="CreateAccount()"/>
            
        </Group>

    </Contents>

</UITemplate>
    